LICENSE
ws_master/__init__.py
ws_master/client.py
ws_master/event/__init__.py
ws_master/event/event.py
ws_master/event/response/__init__.py
ws_master/event/response/builder.py
ws_master/event/response/response.py
ws_master/event/response/strategies/__init__.py
ws_master/event/response/strategies/abstracts.py
ws_master/event/response/strategies/strategies.py
ws_master/exceptions.py
ws_master/file_builder.py
ws_master/handler.py
ws_master/injector.py
ws_master/router.py
ws_master/schemas.py
ws_master/services.py
websocket_master_fastapi-0.1.42.dist-info/LICENSE
websocket_master_fastapi-0.1.42.dist-info/METADATA
websocket_master_fastapi-0.1.42.dist-info/WHEEL
websocket_master_fastapi-0.1.42.dist-info/entry_points.txt
websocket_master_fastapi-0.1.42.dist-info/RECORD
